{
	"page": {
		"title": "MUGEN Trigger",
		"subtitle": "E",
		"target": "数学",
		"category": ["定数", "自然対数の底は？"],
		"version": "2002.04.14",
		"update": "2016.12.11",
		"type": "document",
		"level": "3"
	},
	"category": "trigger",

	"trigger": "E",
	"summary": "<p>ネピア数(自然対数の底)を返します。</p>",
	"syntax":[
		"E"
	],

	"description": "<p>定数(<script>document.write(Math.E);</script>)を返します。</p><p>戻り値の型: float</p>",

	"code_sample": [
		{
			"title": "Eは計算によって、なぜか違う値を返してきます",
			"code": [
				"[State ]",
				"Type = Null",
				"",
				";2.718282",
				"Trigger1 = E",
				"",
				";27.182817",
				"Trigger1 = E*10",
				"",
				";271.828186",
				"Trigger1 = E*100",
				"",
				";2718.281738",
				"Trigger1 = E*1000",
				"",
				";27182.818359",
				"Trigger1 = E*10000",
				"",
				";271828.187500",
				"Trigger1 = E*100000",
				"",
				";2718281.750000",
				"Trigger1 = E*1000000",
				"",
				";27182818.000000",
				"Trigger1 = E*10000000",
				"",
				";271828160.000000",
				"Trigger1 = E*100000000",
				"",
				";2718281728.000000",
				"Trigger1 = E*1000000000",
				"",
				";5837465600.000000",
				"Trigger1 = E*10000000000",
				"",
				";7.389056",
				"Trigger1 = E*E"
			]
		}
	],

	"associated_trigger": ["Exp"],

	"quote": [
		{"title": "E - Trigger Reference(version 2002.04.14)", "url": "/MUGEN/document/Official/2002.04.14/trigger.html#E"},
		{"title": "E - Trigger Reference(version 1.0)", "url": "https://web.archive.org/web/http://www.elecbyte.com/mugendocs/trigger.html#e-math"},
		{"title": "E - Trigger Reference(version 1.1)", "url": "https://web.archive.org/web/http://www.elecbyte.com/mugendocs-11b1/trigger.html#e-math"},
		{"title": "E - M.U.G.E.N wiki", "url": "https://web.archive.org/web/http://elecbyte.com/wiki/index.php/E"},
		{"title": "E - MUGEN CNS WIKI CHAOS@予定", "url": "https://www49.atwiki.jp/mugencns/pages/117.html"}
	]
}